{
    "format_version": "1.20.10",
    "minecraft:recipe_shaped": {
        "description": {
            "identifier": "edx:sandy_stonebrick_slab"
        },
        "tags": [
            "crafting_table"
        ],
        "pattern": [
            "WWW"
        ],
        "key": {
            "W": {
                "item": "edx:sandy_stonebrick"
            }
        },
        "unlock": [
            {
                "item": "edx:sandy_stonebrick"
            }
        ],
        "result": {
            "item": "edx:sandy_stonebrick_slab",
            "count": 6
        }
    }
}