{
    "format_version": "1.17.0",
    "minecraft:single_block_feature": {
        "description": {
          "identifier": "edx:eye_feature"
        },
        "places_block":{
            "name": "edx:eye_bulb",
            "states": {
                "edx:stage": 3
            }
        },
        "enforce_placement_rules": true,
        "enforce_survivability_rules": true,
        "may_attach_to": {
          "bottom":  [
            "minecraft:soul_soil"
        ]
      },
        "may_replace": [
          "minecraft:air"
        ]
      }
}